Changelog.md
MANIFEST.in
README.md
setup.cfg
setup.py
openid/__init__.py
openid/association.py
openid/constants.py
openid/cryptutil.py
openid/dh.py
openid/extension.py
openid/fetchers.py
openid/kvform.py
openid/message.py
openid/oidutil.py
openid/sreg.py
openid/urinorm.py
openid/consumer/__init__.py
openid/consumer/consumer.py
openid/consumer/discover.py
openid/extensions/__init__.py
openid/extensions/ax.py
openid/extensions/pape.py
openid/extensions/sreg.py
openid/extensions/draft/__init__.py
openid/extensions/draft/pape2.py
openid/extensions/draft/pape5.py
openid/server/__init__.py
openid/server/server.py
openid/server/trustroot.py
openid/store/__init__.py
openid/store/filestore.py
openid/store/interface.py
openid/store/memstore.py
openid/store/nonce.py
openid/store/sqlstore.py
openid/yadis/__init__.py
openid/yadis/accept.py
openid/yadis/constants.py
openid/yadis/discover.py
openid/yadis/etxrd.py
openid/yadis/filters.py
openid/yadis/manager.py
openid/yadis/parsehtml.py
openid/yadis/services.py
openid/yadis/xri.py
openid/yadis/xrires.py
python_openid2.egg-info/PKG-INFO
python_openid2.egg-info/SOURCES.txt
python_openid2.egg-info/dependency_links.txt
python_openid2.egg-info/requires.txt
python_openid2.egg-info/top_level.txt